optimodel_types/__init__.py
optimodel_types/providerTypes.py
optimodel_types-0.3.0.dist-info/METADATA
optimodel_types-0.3.0.dist-info/WHEEL
optimodel_types-0.3.0.dist-info/top_level.txt
optimodel_types-0.3.0.dist-info/RECORD
