Metadata-Version: 2.1
Name: optimodel-types
Version: 0.3.0
Summary: A smart framework for calling models in the most efficient way possible
Author-email: Lytix <support@lytix.com>
Project-URL: Homepage, https://github.com/Lytix-Labs/optimodel
Project-URL: Issues, https://github.com/Lytix-Labs/optimodel/issues
Classifier: Programming Language :: Python :: 3
Classifier: License :: OSI Approved :: MIT License
Classifier: Operating System :: OS Independent
Requires-Python: >=3.8
